{
    "analyse": [{
        "placeName": "Galle International Stadium, Galle Galle District Southern Province",
        "positivePresentage": 100.0,
        "negativePresentage": 0.0,
        "naturalPresentage": 0.0,
        "totalPolarity": 1.9402777777777775,
        "totalReviews": 5,
        "polarityis": [0.18611111111111112, 0.7999999999999999, 0.2475, 0.26666666666666666, 0.44],
        "subjectivities": [0.44037037037037036, 0.9166666666666666, 0.5547222222222222, 0.6066666666666667, 0.76],
        "bestReview": "The stadium looks really nice from the fort. It was a great feeling to observe cricket being played at the stadium. The setting is just marvelous."
    }, {
        "placeName": "Galle International Stadium, Galle Galle District Southern Province",
        "positivePresentage": 100.0,
        "negativePresentage": 0.0,
        "naturalPresentage": 0.0,
        "totalPolarity": 1.8322916666666664,
        "totalReviews": 5,
        "polarityis": [0.7999999999999999, 0.2475, 0.26666666666666666, 0.44, 0.078125],
        "subjectivities": [0.9166666666666666, 0.5547222222222222, 0.6066666666666667, 0.76, 0.2708333333333333],
        "bestReview": "The stadium looks really nice from the fort. It was a great feeling to observe cricket being played at the stadium. The setting is just marvelous."
    }, {
        "placeName": "Galle International Stadium, Galle Galle District Southern Province",
        "positivePresentage": 100.0,
        "negativePresentage": 0.0,
        "naturalPresentage": 0.0,
        "totalPolarity": 1.177746212121212,
        "totalReviews": 5,
        "polarityis": [0.2475, 0.26666666666666666, 0.44, 0.078125, 0.14545454545454548],
        "subjectivities": [0.5547222222222222, 0.6066666666666667, 0.76, 0.2708333333333333, 0.3],
        "bestReview": "I didn't enter the stadium but watched the scenic view from the galle fort. Wow simply awesome stadium touching distance from the sea. It should be one of the scenic stadiums in the world where there is a high possibility that the ball one day will be hit into the sea."
    }, {
        "placeName": "Galle International Stadium, Galle Galle District Southern Province",
        "positivePresentage": 100.0,
        "negativePresentage": 0.0,
        "naturalPresentage": 0.0,
        "totalPolarity": 1.0302462121212121,
        "totalReviews": 5,
        "polarityis": [0.26666666666666666, 0.44, 0.078125, 0.14545454545454548, 0.10000000000000002],
        "subjectivities": [0.6066666666666667, 0.76, 0.2708333333333333, 0.3, 0.325],
        "bestReview": "I didn't enter the stadium but watched the scenic view from the galle fort. Wow simply awesome stadium touching distance from the sea. It should be one of the scenic stadiums in the world where there is a high possibility that the ball one day will be hit into the sea."
    }, {
        "placeName": "Galle International Stadium, Galle Galle District Southern Province",
        "positivePresentage": 100.0,
        "negativePresentage": 0.0,
        "naturalPresentage": 0.0,
        "totalPolarity": 0.8969128787878788,
        "totalReviews": 5,
        "polarityis": [0.44, 0.078125, 0.14545454545454548, 0.10000000000000002, 0.13333333333333336],
        "subjectivities": [0.76, 0.2708333333333333, 0.3, 0.325, 0.6361111111111111],
        "bestReview": "I didn't enter the stadium but watched the scenic view from the galle fort. Wow simply awesome stadium touching distance from the sea. It should be one of the scenic stadiums in the world where there is a high possibility that the ball one day will be hit into the sea."
    }, {
        "placeName": "Old Town of Galle and its Fortifications, Galle Galle District Southern Province",
        "positivePresentage": 100.0,
        "negativePresentage": 0.0,
        "naturalPresentage": 0.0,
        "totalPolarity": 2.0147182539682538,
        "totalReviews": 7,
        "polarityis": [0.22827380952380952, 0.25, 0.17533333333333329, 0.1625, 0.25999999999999995, 0.6177777777777776, 0.32083333333333336],
        "subjectivities": [0.4440476190476191, 0.5375, 0.6326666666666667, 0.75, 0.31, 0.7666666666666666, 0.7000000000000001],
        "bestReview": "This is a very pleasant town to walk around.  Start at the clock tower and walk along the fortifications taking in the main bastion then on to the mosque and the lighthouse before going to see the Dutch Fort, Dutch Hospital & Dutch church. We had a pleasant lunch at the Rampart Hotel overlooking the sea."
    }, {
        "placeName": "Old Town of Galle and its Fortifications, Galle Galle District Southern Province",
        "positivePresentage": 85.71,
        "negativePresentage": 14.29,
        "naturalPresentage": 0.0,
        "totalPolarity": 1.4197777777777776,
        "totalReviews": 7,
        "polarityis": [0.25, 0.17533333333333329, 0.1625, 0.25999999999999995, 0.6177777777777776, 0.32083333333333336, -0.3666666666666667],
        "subjectivities": [0.5375, 0.6326666666666667, 0.75, 0.31, 0.7666666666666666, 0.7000000000000001, 0.7333333333333334],
        "bestReview": "This is a very pleasant town to walk around.  Start at the clock tower and walk along the fortifications taking in the main bastion then on to the mosque and the lighthouse before going to see the Dutch Fort, Dutch Hospital & Dutch church. We had a pleasant lunch at the Rampart Hotel overlooking the sea."
    }, {
        "placeName": "Old Town of Galle and its Fortifications, Galle Galle District Southern Province",
        "positivePresentage": 85.71,
        "negativePresentage": 14.29,
        "naturalPresentage": 0.0,
        "totalPolarity": 1.3597777777777775,
        "totalReviews": 7,
        "polarityis": [0.17533333333333329, 0.1625, 0.25999999999999995, 0.6177777777777776, 0.32083333333333336, -0.3666666666666667, 0.19],
        "subjectivities": [0.6326666666666667, 0.75, 0.31, 0.7666666666666666, 0.7000000000000001, 0.7333333333333334, 0.55],
        "bestReview": "This is a very pleasant town to walk around.  Start at the clock tower and walk along the fortifications taking in the main bastion then on to the mosque and the lighthouse before going to see the Dutch Fort, Dutch Hospital & Dutch church. We had a pleasant lunch at the Rampart Hotel overlooking the sea."
    }, {
        "placeName": "Old Town of Galle and its Fortifications, Galle Galle District Southern Province",
        "positivePresentage": 80.0,
        "negativePresentage": 20.0,
        "naturalPresentage": 0.0,
        "totalPolarity": 1.0744444444444443,
        "totalReviews": 5,
        "polarityis": [0.6177777777777776, 0.32083333333333336, -0.3666666666666667, 0.19, 0.3125],
        "subjectivities": [0.7666666666666666, 0.7000000000000001, 0.7333333333333334, 0.55, 0.5],
        "bestReview": "This is a very pleasant town to walk around.  Start at the clock tower and walk along the fortifications taking in the main bastion then on to the mosque and the lighthouse before going to see the Dutch Fort, Dutch Hospital & Dutch church. We had a pleasant lunch at the Rampart Hotel overlooking the sea."
    }, {
        "placeName": "Old Town of Galle and its Fortifications, Galle Galle District Southern Province",
        "positivePresentage": 80.0,
        "negativePresentage": 20.0,
        "naturalPresentage": 0.0,
        "totalPolarity": 0.6173809523809524,
        "totalReviews": 5,
        "polarityis": [0.32083333333333336, -0.3666666666666667, 0.19, 0.3125, 0.16071428571428573],
        "subjectivities": [0.7000000000000001, 0.7333333333333334, 0.55, 0.5, 0.4642857142857143],
        "bestReview": "Galle is a lovely small town rich in culture and history. It's a nice place to walk around. I would recommend catching the sunset near the lighthouse."
    }, {
        "placeName": "Sinharaja Forest Reserve, Galle Galle District Southern Province",
        "positivePresentage": 50.0,
        "negativePresentage": 40.0,
        "naturalPresentage": 10.0,
        "totalPolarity": 1.1327002164502165,
        "totalReviews": 10,
        "polarityis": [0.3568371212121212, 0.056696428571428564, 0.45, -0.0625, 0.0, -0.018333333333333333, 0.65, -0.16666666666666666, -0.20833333333333334, 0.07500000000000002],
        "subjectivities": [0.5845265151515152, 0.4580357142857143, 0.65, 0.3375, 0.0, 0.5883333333333333, 0.825, 0.4555555555555555, 0.7916666666666666, 0.59],
        "bestReview": "The waterfall / swimming was a welcome relief and lovely."
    }, {
        "placeName": "Sinharaja Forest Reserve, Galle Galle District Southern Province",
        "positivePresentage": 50.0,
        "negativePresentage": 40.0,
        "naturalPresentage": 10.0,
        "totalPolarity": 1.1276488095238095,
        "totalReviews": 10,
        "polarityis": [0.056696428571428564, 0.45, -0.0625, 0.0, -0.018333333333333333, 0.65, -0.16666666666666666, -0.20833333333333334, 0.07500000000000002, 0.35178571428571426],
        "subjectivities": [0.4580357142857143, 0.65, 0.3375, 0.0, 0.5883333333333333, 0.825, 0.4555555555555555, 0.7916666666666666, 0.59, 0.551984126984127],
        "bestReview": "The waterfall / swimming was a welcome relief and lovely."
    }, {
        "placeName": "Sinharaja Forest Reserve, Galle Galle District Southern Province",
        "positivePresentage": 50.0,
        "negativePresentage": 40.0,
        "naturalPresentage": 10.0,
        "totalPolarity": 1.4227380952380955,
        "totalReviews": 10,
        "polarityis": [0.45, -0.0625, 0.0, -0.018333333333333333, 0.65, -0.16666666666666666, -0.20833333333333334, 0.07500000000000002, 0.35178571428571426, 0.35178571428571426],
        "subjectivities": [0.65, 0.3375, 0.0, 0.5883333333333333, 0.825, 0.4555555555555555, 0.7916666666666666, 0.59, 0.551984126984127, 0.551984126984127],
        "bestReview": "The waterfall / swimming was a welcome relief and lovely."
    }, {
        "placeName": "Sinharaja Forest Reserve, Galle Galle District Southern Province",
        "positivePresentage": 80.0,
        "negativePresentage": 20.0,
        "naturalPresentage": 0.0,
        "totalPolarity": 0.6369047619047619,
        "totalReviews": 5,
        "polarityis": [-0.20833333333333334, 0.07500000000000002, 0.35178571428571426, 0.35178571428571426, 0.06666666666666667],
        "subjectivities": [0.7916666666666666, 0.59, 0.551984126984127, 0.551984126984127, 0.06666666666666667],
        "bestReview": "I brought my nature-loving twin in Sinharaja Forest Reserve, and she has never been happier. The hilly virgin rainforest was so lush and green. It\u2019s surely a gem of endemic species of mammals, birds, and reptiles. I love how the government was able to preserve the natural beauty of this spot! Remarkable indeed!"
    }, {
        "placeName": "Sinharaja Forest Reserve, Galle Galle District Southern Province",
        "positivePresentage": 100.0,
        "negativePresentage": 0.0,
        "naturalPresentage": 0.0,
        "totalPolarity": 1.361904761904762,
        "totalReviews": 5,
        "polarityis": [0.07500000000000002, 0.35178571428571426, 0.35178571428571426, 0.06666666666666667, 0.5166666666666667],
        "subjectivities": [0.59, 0.551984126984127, 0.551984126984127, 0.06666666666666667, 0.7666666666666666],
        "bestReview": "Amazing scenery and a must see when visiting Sri Lanka. Beautiful waterfalls and hundreds of wild life. "
    }, {
        "placeName": "Galle Fort Lighthouse, Galle Galle District Southern Province",
        "positivePresentage": 100.0,
        "negativePresentage": 0.0,
        "naturalPresentage": 0.0,
        "totalPolarity": 1.8604166666666666,
        "totalReviews": 5,
        "polarityis": [0.25, 0.7333333333333333, 0.20625, 0.4375, 0.23333333333333336],
        "subjectivities": [0.39999999999999997, 0.9666666666666667, 0.7, 0.3375, 0.3833333333333333],
        "bestReview": "The lighthouse is a pleasant to look at building whilst walking along the line of the fortifications."
    }, {
        "placeName": "Galle Fort Lighthouse, Galle Galle District Southern Province",
        "positivePresentage": 100.0,
        "negativePresentage": 0.0,
        "naturalPresentage": 0.0,
        "totalPolarity": 1.8104166666666666,
        "totalReviews": 5,
        "polarityis": [0.7333333333333333, 0.20625, 0.4375, 0.23333333333333336, 0.2],
        "subjectivities": [0.9666666666666667, 0.7, 0.3375, 0.3833333333333333, 0.35000000000000003],
        "bestReview": "The lighthouse is a pleasant to look at building whilst walking along the line of the fortifications."
    }, {
        "placeName": "Galle Fort Lighthouse, Galle Galle District Southern Province",
        "positivePresentage": 100.0,
        "negativePresentage": 0.0,
        "naturalPresentage": 0.0,
        "totalPolarity": 1.7770833333333333,
        "totalReviews": 5,
        "polarityis": [0.20625, 0.4375, 0.23333333333333336, 0.2, 0.7],
        "subjectivities": [0.7, 0.3375, 0.3833333333333333, 0.35000000000000003, 0.6000000000000001],
        "bestReview": "You can have a good view of the coastline and sea from here . A good place to set  your orientation . "
    }, {
        "placeName": "Galle Fort Lighthouse, Galle Galle District Southern Province",
        "positivePresentage": 100.0,
        "negativePresentage": 0.0,
        "naturalPresentage": 0.0,
        "totalPolarity": 1.7145833333333333,
        "totalReviews": 5,
        "polarityis": [0.4375, 0.23333333333333336, 0.2, 0.7, 0.14375],
        "subjectivities": [0.3375, 0.3833333333333333, 0.35000000000000003, 0.6000000000000001, 0.39375000000000004],
        "bestReview": "You can have a good view of the coastline and sea from here . A good place to set  your orientation . "
    }, {
        "placeName": "Galle Fort Lighthouse, Galle Galle District Southern Province",
        "positivePresentage": 80.0,
        "negativePresentage": 20.0,
        "naturalPresentage": 0.0,
        "totalPolarity": 1.1580357142857143,
        "totalReviews": 5,
        "polarityis": [0.23333333333333336, 0.2, 0.7, 0.14375, -0.11904761904761905],
        "subjectivities": [0.3833333333333333, 0.35000000000000003, 0.6000000000000001, 0.39375000000000004, 0.2261904761904762],
        "bestReview": "You can have a good view of the coastline and sea from here . A good place to set  your orientation . "
    }, {
        "placeName": "Galle Fort, Galle Galle District Southern Province",
        "positivePresentage": 100.0,
        "negativePresentage": 0.0,
        "naturalPresentage": 0.0,
        "totalPolarity": 3.163755291005291,
        "totalReviews": 9,
        "polarityis": [0.3527777777777778, 0.3201904761904762, 0.6, 0.11689814814814814, 0.041666666666666664, 0.48888888888888893, 0.5, 0.5666666666666667, 0.17666666666666667],
        "subjectivities": [0.41018518518518526, 0.5336190476190475, 0.6833333333333332, 0.5407407407407407, 0.5483333333333333, 0.7999999999999999, 0.7, 0.7000000000000001, 0.505],
        "bestReview": "Short trip from hotel by tuk tuk. Great views out to sea from the fortress walls with a cooling breeze. Excellent photo opportunity."
    }, {
        "placeName": "Galle Fort, Galle Galle District Southern Province",
        "positivePresentage": 100.0,
        "negativePresentage": 0.0,
        "naturalPresentage": 0.0,
        "totalPolarity": 3.250977513227513,
        "totalReviews": 9,
        "polarityis": [0.3201904761904762, 0.6, 0.11689814814814814, 0.041666666666666664, 0.48888888888888893, 0.5, 0.5666666666666667, 0.17666666666666667, 0.43999999999999995],
        "subjectivities": [0.5336190476190475, 0.6833333333333332, 0.5407407407407407, 0.5483333333333333, 0.7999999999999999, 0.7, 0.7000000000000001, 0.505, 0.4600000000000001],
        "bestReview": "Short trip from hotel by tuk tuk. Great views out to sea from the fortress walls with a cooling breeze. Excellent photo opportunity."
    }, {
        "placeName": "Galle Fort, Galle Galle District Southern Province",
        "positivePresentage": 100.0,
        "negativePresentage": 0.0,
        "naturalPresentage": 0.0,
        "totalPolarity": 3.1974537037037036,
        "totalReviews": 9,
        "polarityis": [0.6, 0.11689814814814814, 0.041666666666666664, 0.48888888888888893, 0.5, 0.5666666666666667, 0.17666666666666667, 0.43999999999999995, 0.26666666666666666],
        "subjectivities": [0.6833333333333332, 0.5407407407407407, 0.5483333333333333, 0.7999999999999999, 0.7, 0.7000000000000001, 0.505, 0.4600000000000001, 0.19999999999999998],
        "bestReview": "Short trip from hotel by tuk tuk. Great views out to sea from the fortress walls with a cooling breeze. Excellent photo opportunity."
    }, {
        "placeName": "Galle Fort, Galle Galle District Southern Province",
        "positivePresentage": 100.0,
        "negativePresentage": 0.0,
        "naturalPresentage": 0.0,
        "totalPolarity": 1.8666666666666663,
        "totalReviews": 5,
        "polarityis": [0.5666666666666667, 0.17666666666666667, 0.43999999999999995, 0.26666666666666666, 0.4166666666666666],
        "subjectivities": [0.7000000000000001, 0.505, 0.4600000000000001, 0.19999999999999998, 0.5708333333333333],
        "bestReview": "Fortification built by Portuguese in 16th century and extended by Dutch in 18th during the colonial era. Nice place to enjoy the sea Breeze with good sea view, but should do it during morning or evening time since afternoon sun can be scorching visiting at this place. Some of the highlights are the clock tower, the lighthouse, etc. "
    }, {
        "placeName": "Galle Fort, Galle Galle District Southern Province",
        "positivePresentage": 100.0,
        "negativePresentage": 0.0,
        "naturalPresentage": 0.0,
        "totalPolarity": 1.7499999999999998,
        "totalReviews": 5,
        "polarityis": [0.17666666666666667, 0.43999999999999995, 0.26666666666666666, 0.4166666666666666, 0.45],
        "subjectivities": [0.505, 0.4600000000000001, 0.19999999999999998, 0.5708333333333333, 0.7314814814814814],
        "bestReview": "This was a nice walk along the tops of the fortifications. It was not spectacular but pleasant. Make sure that you go out onto the main bastion to get the best views."
    }, {
        "placeName": "Dalawella Beach, Galle Galle District Southern Province",
        "positivePresentage": 87.5,
        "negativePresentage": 12.5,
        "naturalPresentage": 0.0,
        "totalPolarity": 1.0177678571428572,
        "totalReviews": 8,
        "polarityis": [0.2333333333333333, 0.125, 0.24047619047619048, 0.32, -0.6, 0.39999999999999997, 0.15833333333333333, 0.140625],
        "subjectivities": [0.4666666666666666, 0.37642857142857145, 0.661904761904762, 0.72, 0.5, 0.8, 0.5870370370370371, 0.85],
        "bestReview": "Restaurants along the beach here are good. A make shift cafe at the far end for a breeze and lounger on the sand. "
    }, {
        "placeName": "Dalawella Beach, Galle Galle District Southern Province",
        "positivePresentage": 85.71,
        "negativePresentage": 14.29,
        "naturalPresentage": 0.0,
        "totalPolarity": 0.6719345238095238,
        "totalReviews": 7,
        "polarityis": [0.24047619047619048, 0.32, -0.6, 0.39999999999999997, 0.15833333333333333, 0.140625, 0.012499999999999997],
        "subjectivities": [0.661904761904762, 0.72, 0.5, 0.8, 0.5870370370370371, 0.85, 0.6249999999999999],
        "bestReview": "Restaurants along the beach here are good. A make shift cafe at the far end for a breeze and lounger on the sand. "
    }, {
        "placeName": "Dalawella Beach, Galle Galle District Southern Province",
        "positivePresentage": 85.71,
        "negativePresentage": 14.29,
        "naturalPresentage": 0.0,
        "totalPolarity": 0.6925694444444445,
        "totalReviews": 7,
        "polarityis": [0.32, -0.6, 0.39999999999999997, 0.15833333333333333, 0.140625, 0.012499999999999997, 0.2611111111111111],
        "subjectivities": [0.72, 0.5, 0.8, 0.5870370370370371, 0.85, 0.6249999999999999, 0.44111111111111106],
        "bestReview": "Restaurants along the beach here are good. A make shift cafe at the far end for a breeze and lounger on the sand. "
    }, {
        "placeName": "Dalawella Beach, Galle Galle District Southern Province",
        "positivePresentage": 85.71,
        "negativePresentage": 14.29,
        "naturalPresentage": 0.0,
        "totalPolarity": 0.7915873015873016,
        "totalReviews": 7,
        "polarityis": [0.15833333333333333, 0.140625, 0.012499999999999997, 0.2611111111111111, 0.12068452380952381, -0.125, 0.22333333333333336],
        "subjectivities": [0.5870370370370371, 0.85, 0.6249999999999999, 0.44111111111111106, 0.34603174603174597, 0.375, 0.59],
        "bestReview": "Definitely good spot for a travel pic but not necessarily as hidden and dreamy as promoted. Had to pay 500lk to do the swing and had to take a turn in very low season after the attacks (so no tourists in sight apart from us)"
    }, {
        "placeName": "Dalawella Beach, Galle Galle District Southern Province",
        "positivePresentage": 87.5,
        "negativePresentage": 12.5,
        "naturalPresentage": 0.0,
        "totalPolarity": 1.5665873015873015,
        "totalReviews": 8,
        "polarityis": [0.140625, 0.012499999999999997, 0.2611111111111111, 0.12068452380952381, -0.125, 0.22333333333333336, 0.4333333333333333, 0.5],
        "subjectivities": [0.85, 0.6249999999999999, 0.44111111111111106, 0.34603174603174597, 0.375, 0.59, 0.4833333333333334, 0.75],
        "bestReview": "I would recommend you but there are some better options :) "
    }, {
        "placeName": "Sea Turtle Farm Galle Mahamodara, Galle Galle District Southern Province",
        "positivePresentage": 100.0,
        "negativePresentage": 0.0,
        "naturalPresentage": 0.0,
        "totalPolarity": 1.6777782788199456,
        "totalReviews": 5,
        "polarityis": [0.16979166666666667, 0.3645342312008979, 0.13095238095238096, 0.75, 0.2625],
        "subjectivities": [0.5261904761904762, 0.5214927048260382, 0.5326719576719577, 1.0, 0.3],
        "bestReview": "Really nice visit! The guide was so nice and explaning all the details about the turtles, A must visist!"
    }, {
        "placeName": "Sea Turtle Farm Galle Mahamodara, Galle Galle District Southern Province",
        "positivePresentage": 100.0,
        "negativePresentage": 0.0,
        "naturalPresentage": 0.0,
        "totalPolarity": 1.814236612153279,
        "totalReviews": 5,
        "polarityis": [0.3645342312008979, 0.13095238095238096, 0.75, 0.2625, 0.30625],
        "subjectivities": [0.5214927048260382, 0.5326719576719577, 1.0, 0.3, 0.41874999999999996],
        "bestReview": "Really nice visit! The guide was so nice and explaning all the details about the turtles, A must visist!"
    }, {
        "placeName": "Sea Turtle Farm Galle Mahamodara, Galle Galle District Southern Province",
        "positivePresentage": 100.0,
        "negativePresentage": 0.0,
        "naturalPresentage": 0.0,
        "totalPolarity": 2.856889880952381,
        "totalReviews": 6,
        "polarityis": [0.13095238095238096, 0.75, 0.2625, 0.30625, 0.4071875, 1.0],
        "subjectivities": [0.5326719576719577, 1.0, 0.3, 0.41874999999999996, 0.5975, 0.6000000000000001],
        "bestReview": "Well done to all the team there and keep up the good work guys !!! Cheers !!"
    }, {
        "placeName": "Sea Turtle Farm Galle Mahamodara, Galle Galle District Southern Province",
        "positivePresentage": 100.0,
        "negativePresentage": 0.0,
        "naturalPresentage": 0.0,
        "totalPolarity": 3.3592708333333334,
        "totalReviews": 6,
        "polarityis": [0.75, 0.2625, 0.30625, 0.4071875, 1.0, 0.6333333333333334],
        "subjectivities": [1.0, 0.3, 0.41874999999999996, 0.5975, 0.6000000000000001, 0.7166666666666667],
        "bestReview": "Well done to all the team there and keep up the good work guys !!! Cheers !!"
    }, {
        "placeName": "Sea Turtle Farm Galle Mahamodara, Galle Galle District Southern Province",
        "positivePresentage": 83.33,
        "negativePresentage": 16.67,
        "naturalPresentage": 0.0,
        "totalPolarity": 2.2967708333333334,
        "totalReviews": 6,
        "polarityis": [0.2625, 0.30625, 0.4071875, 1.0, 0.6333333333333334, -0.3125],
        "subjectivities": [0.3, 0.41874999999999996, 0.5975, 0.6000000000000001, 0.7166666666666667, 0.4],
        "bestReview": "Well done to all the team there and keep up the good work guys !!! Cheers !!"
    }, {
        "placeName": "Martin Wickramasinghe Folk Museum Complex, Galle Galle District Southern Province",
        "positivePresentage": 83.33,
        "negativePresentage": 16.67,
        "naturalPresentage": 0.0,
        "totalPolarity": 1.557440476190476,
        "totalReviews": 6,
        "polarityis": [0.171875, 0.7, 0.11785714285714285, 0.35, -0.03229166666666667, 0.25],
        "subjectivities": [0.4875, 0.875, 0.7071428571428571, 0.375, 0.4305555555555556, 0.27777777777777773],
        "bestReview": "Great explanation of the life and work of Mr. Martin Wickramasinghe...... The house is preserved nicely to show the ancient Sri Lankan culture...."
    }, {
        "placeName": "Martin Wickramasinghe Folk Museum Complex, Galle Galle District Southern Province",
        "positivePresentage": 83.33,
        "negativePresentage": 16.67,
        "naturalPresentage": 0.0,
        "totalPolarity": 1.4091765873015871,
        "totalReviews": 6,
        "polarityis": [0.7, 0.11785714285714285, 0.35, -0.03229166666666667, 0.25, 0.023611111111111104],
        "subjectivities": [0.875, 0.7071428571428571, 0.375, 0.4305555555555556, 0.27777777777777773, 0.6972222222222222],
        "bestReview": "Great explanation of the life and work of Mr. Martin Wickramasinghe...... The house is preserved nicely to show the ancient Sri Lankan culture...."
    }, {
        "placeName": "Martin Wickramasinghe Folk Museum Complex, Galle Galle District Southern Province",
        "positivePresentage": 83.33,
        "negativePresentage": 16.67,
        "naturalPresentage": 0.0,
        "totalPolarity": 1.1041765873015872,
        "totalReviews": 6,
        "polarityis": [0.11785714285714285, 0.35, -0.03229166666666667, 0.25, 0.023611111111111104, 0.395],
        "subjectivities": [0.7071428571428571, 0.375, 0.4305555555555556, 0.27777777777777773, 0.6972222222222222, 0.4916666666666667],
        "bestReview": "Martin Wickramainghe is a very important writer and person in the development of the modern Sri Lanka. Most of the museum is display of Sri Lankan folklore, but the house he was born in is very interesting. Most of his books, translated into English can be purchased at the museum."
    }, {
        "placeName": "Martin Wickramasinghe Folk Museum Complex, Galle Galle District Southern Province",
        "positivePresentage": 83.33,
        "negativePresentage": 16.67,
        "naturalPresentage": 0.0,
        "totalPolarity": 1.2941319444444446,
        "totalReviews": 6,
        "polarityis": [0.35, -0.03229166666666667, 0.25, 0.023611111111111104, 0.395, 0.30781250000000004],
        "subjectivities": [0.375, 0.4305555555555556, 0.27777777777777773, 0.6972222222222222, 0.4916666666666667, 0.6],
        "bestReview": "Martin Wickramainghe is a very important writer and person in the development of the modern Sri Lanka. Most of the museum is display of Sri Lankan folklore, but the house he was born in is very interesting. Most of his books, translated into English can be purchased at the museum."
    }, {
        "placeName": "Martin Wickramasinghe Folk Museum Complex, Galle Galle District Southern Province",
        "positivePresentage": 83.33,
        "negativePresentage": 16.67,
        "naturalPresentage": 0.0,
        "totalPolarity": 1.2241319444444445,
        "totalReviews": 6,
        "polarityis": [-0.03229166666666667, 0.25, 0.023611111111111104, 0.395, 0.30781250000000004, 0.27999999999999997],
        "subjectivities": [0.4305555555555556, 0.27777777777777773, 0.6972222222222222, 0.4916666666666667, 0.6, 0.72],
        "bestReview": "Martin Wickramainghe is a very important writer and person in the development of the modern Sri Lanka. Most of the museum is display of Sri Lankan folklore, but the house he was born in is very interesting. Most of his books, translated into English can be purchased at the museum."
    }, {
        "placeName": "Dutch Hospital Shopping Precinct, Galle Galle District Southern Province",
        "positivePresentage": 100.0,
        "negativePresentage": 0.0,
        "naturalPresentage": 0.0,
        "totalPolarity": 1.8888888888888886,
        "totalReviews": 5,
        "polarityis": [0.5444444444444444, 0.25, 0.2833333333333333, 0.4611111111111111, 0.3499999999999999],
        "subjectivities": [0.688888888888889, 0.45, 0.4166666666666667, 0.5611111111111111, 0.3666666666666667],
        "bestReview": "A nice colonade of shops, bars etc.  Worth looking at whilst you are walking around town. There is a pleasant bar on the sea side of the building where one can stop for a cooling drink."
    }, {
        "placeName": "Dutch Hospital Shopping Precinct, Galle Galle District Southern Province",
        "positivePresentage": 100.0,
        "negativePresentage": 0.0,
        "naturalPresentage": 0.0,
        "totalPolarity": 2.106444444444444,
        "totalReviews": 6,
        "polarityis": [0.25, 0.2833333333333333, 0.4611111111111111, 0.3499999999999999, 0.162, 0.6],
        "subjectivities": [0.45, 0.4166666666666667, 0.5611111111111111, 0.3666666666666667, 0.558, 1.0],
        "bestReview": "Nice area to stroll around though."
    }, {
        "placeName": "Dutch Hospital Shopping Precinct, Galle Galle District Southern Province",
        "positivePresentage": 100.0,
        "negativePresentage": 0.0,
        "naturalPresentage": 0.0,
        "totalPolarity": 2.0609898989898987,
        "totalReviews": 6,
        "polarityis": [0.2833333333333333, 0.4611111111111111, 0.3499999999999999, 0.162, 0.6, 0.20454545454545453],
        "subjectivities": [0.4166666666666667, 0.5611111111111111, 0.3666666666666667, 0.558, 1.0, 0.2943181818181818],
        "bestReview": "Nice area to stroll around though."
    }, {
        "placeName": "Dutch Hospital Shopping Precinct, Galle Galle District Southern Province",
        "positivePresentage": 100.0,
        "negativePresentage": 0.0,
        "naturalPresentage": 0.0,
        "totalPolarity": 1.968212121212121,
        "totalReviews": 6,
        "polarityis": [0.4611111111111111, 0.3499999999999999, 0.162, 0.6, 0.20454545454545453, 0.19055555555555556],
        "subjectivities": [0.5611111111111111, 0.3666666666666667, 0.558, 1.0, 0.2943181818181818, 0.29111111111111115],
        "bestReview": "Nice area to stroll around though."
    }, {
        "placeName": "Dutch Hospital Shopping Precinct, Galle Galle District Southern Province",
        "positivePresentage": 100.0,
        "negativePresentage": 0.0,
        "naturalPresentage": 0.0,
        "totalPolarity": 1.8237676767676767,
        "totalReviews": 6,
        "polarityis": [0.3499999999999999, 0.162, 0.6, 0.20454545454545453, 0.19055555555555556, 0.3166666666666667],
        "subjectivities": [0.3666666666666667, 0.558, 1.0, 0.2943181818181818, 0.29111111111111115, 0.5000000000000001],
        "bestReview": "Nice area to stroll around though."
    }, {
        "placeName": "Dutch Reformed Church, Galle Galle District Southern Province",
        "positivePresentage": 100.0,
        "negativePresentage": 0.0,
        "naturalPresentage": 0.0,
        "totalPolarity": 1.5180555555555555,
        "totalReviews": 5,
        "polarityis": [0.04999999999999999, 0.15138888888888885, 0.55, 0.45, 0.31666666666666665],
        "subjectivities": [0.625, 0.4347222222222223, 0.86875, 0.67, 0.25],
        "bestReview": "Stunning interior and a fascinating history make this a must see stop on any tour of Galle.  We were pushed for time but so glad we were able to have some time here."
    }, {
        "placeName": "Dutch Reformed Church, Galle Galle District Southern Province",
        "positivePresentage": 100.0,
        "negativePresentage": 0.0,
        "naturalPresentage": 0.0,
        "totalPolarity": 1.6880555555555554,
        "totalReviews": 5,
        "polarityis": [0.15138888888888885, 0.55, 0.45, 0.31666666666666665, 0.22000000000000003],
        "subjectivities": [0.4347222222222223, 0.86875, 0.67, 0.25, 0.48],
        "bestReview": "Stunning interior and a fascinating history make this a must see stop on any tour of Galle.  We were pushed for time but so glad we were able to have some time here."
    }, {
        "placeName": "Dutch Reformed Church, Galle Galle District Southern Province",
        "positivePresentage": 100.0,
        "negativePresentage": 0.0,
        "naturalPresentage": 0.0,
        "totalPolarity": 1.7963888888888888,
        "totalReviews": 5,
        "polarityis": [0.55, 0.45, 0.31666666666666665, 0.22000000000000003, 0.25972222222222224],
        "subjectivities": [0.86875, 0.67, 0.25, 0.48, 0.611111111111111],
        "bestReview": "Stunning interior and a fascinating history make this a must see stop on any tour of Galle.  We were pushed for time but so glad we were able to have some time here."
    }, {
        "placeName": "Dutch Reformed Church, Galle Galle District Southern Province",
        "positivePresentage": 100.0,
        "negativePresentage": 0.0,
        "naturalPresentage": 0.0,
        "totalPolarity": 1.5678174603174602,
        "totalReviews": 5,
        "polarityis": [0.45, 0.31666666666666665, 0.22000000000000003, 0.25972222222222224, 0.32142857142857145],
        "subjectivities": [0.67, 0.25, 0.48, 0.611111111111111, 0.4571428571428572],
        "bestReview": "Visited as part of whistle stop Galle visit. Nice enough, lovely history and beautiful views. Worth a visit "
    }, {
        "placeName": "Dutch Reformed Church, Galle Galle District Southern Province",
        "positivePresentage": 100.0,
        "negativePresentage": 0.0,
        "naturalPresentage": 0.0,
        "totalPolarity": 1.2983302808302808,
        "totalReviews": 5,
        "polarityis": [0.31666666666666665, 0.22000000000000003, 0.25972222222222224, 0.32142857142857145, 0.18051282051282053],
        "subjectivities": [0.25, 0.48, 0.611111111111111, 0.4571428571428572, 0.47846153846153844],
        "bestReview": "It's not the most stunning church inside but there is the detail and history. I appreciated the exterior more. I had a guide with me who gave me so much information that I would not have known otherwise. Suggest combining the visit with The National Museum near by (if your interested). "
    }]
}